MondayProcessor/__init__.py
MondayProcessor/__version__.py
MondayProcessor/_fetchBoardById.py
MondayProcessor/_fetchBoardLogsById.py
MondayProcessor/_fetchColumnValueByGroup.py
MondayProcessor/_fetchGroups.py
MondayProcessor/_fetchPrismConf.py
MondayProcessor/_fetchPrismConfByBoard.py
MondayProcessor/_fetchPrismConfByGroup.py
MondayProcessor/_searchColumnIdsByName.py
MondayProcessor/_searchConfColumnIds.py
MondayProcessor/_searchConfColumnIdsMatch.py
MondayProcessor/launchInteractiveProcess.py
MondayProcessor/DataProcessor/__init__.py
MondayProcessor/DataProcessor/launchInteractiveProcess.py
MondayProcessor/MondayProcessorExceptions_/__init__.py
MondayProcessor/MondayProcessorExceptions_/MondayProcessorBoardColumnNotMatch/__init__.py
MondayProcessor/MondayProcessorExceptions_/MondayProcessorBoardNotFound/__init__.py
MondayProcessor/MondayProcessorExceptions_/MondayProcessorException/__init__.py
MondayProcessor/MondayProcessorExceptions_/MondayProcessorNoColumInBoard/__init__.py
MondayProcessor/MondayProcessorExceptions_/MondayProcessorNoGroupsInBoard/__init__.py
MondayProcessor/MondayProcessorExceptions_/MondayProcessorNoItemInGroup/__init__.py
MondayProcessor/MondayProcessorExceptions_/MondayProcessorPageNotSupported/__init__.py
MondayProcessor-0.0.0.dist-info/LICENSE
MondayProcessor-0.0.0.dist-info/METADATA
MondayProcessor-0.0.0.dist-info/WHEEL
MondayProcessor-0.0.0.dist-info/top_level.txt
MondayProcessor-0.0.0.dist-info/RECORD
