Metadata-Version: 2.1
Name: MondayProcessor
Version: 0.0.0
Summary: A library used to fetch information on Monday.com boards.
Author-email: Cody Xiaozhan Yang <xiaozhan.yang@icloud.com>
License: MIT License
Keywords: Monday,API,fetch,processor
Classifier: Programming Language :: Python :: 3
Classifier: License :: OSI Approved :: MIT License
Classifier: Operating System :: OS Independent
Requires-Python: >=3.8
License-File: LICENSE
